{
  "version": "4.5.6",
  "flags": {},
  "shapes": [
    {
      "label": "cirtus1",
      "points": [
        [
          362.5,
          399.0
        ],
        [
          377.5,
          397.75
        ],
        [
          391.25,
          401.5
        ],
        [
          405.0,
          406.5
        ],
        [
          416.25,
          414.0
        ],
        [
          421.25,
          420.25
        ],
        [
          425.0,
          436.5
        ],
        [
          423.75,
          455.25
        ],
        [
          416.25,
          471.5
        ],
        [
          395.0,
          475.25
        ],
        [
          370.0,
          475.25
        ],
        [
          350.0,
          471.5
        ],
        [
          336.25,
          462.75
        ],
        [
          330.0,
          449.0
        ],
        [
          331.25,
          435.25
        ],
        [
          338.75,
          412.75
        ],
        [
          346.25,
          402.75
        ]
      ],
      "group_id": null,
      "shape_type": "polygon",
      "flags": {}
    },
    {
      "label": "cirtus2",
      "points": [
        [
          288.75,
          477.75
        ],
        [
          281.25,
          485.25
        ],
        [
          277.5,
          500.25
        ],
        [
          277.5,
          514.0
        ],
        [
          283.75,
          527.75
        ],
        [
          298.75,
          536.5
        ],
        [
          313.75,
          537.75
        ],
        [
          330.0,
          537.75
        ],
        [
          336.25,
          521.5
        ],
        [
          352.5,
          515.25
        ],
        [
          360.0,
          509.0
        ],
        [
          357.5,
          490.25
        ],
        [
          346.25,
          477.75
        ],
        [
          332.5,
          469.0
        ],
        [
          313.75,
          467.75
        ],
        [
          301.25,
          467.75
        ]
      ],
      "group_id": null,
      "shape_type": "polygon",
      "flags": {}
    },
    {
      "label": "cirtus3",
      "points": [
        [
          717.5,
          317.75
        ],
        [
          731.25,
          312.75
        ],
        [
          751.25,
          315.25
        ],
        [
          768.75,
          321.5
        ],
        [
          787.5,
          341.5
        ],
        [
          790.0,
          355.25
        ],
        [
          787.5,
          374.0
        ],
        [
          776.25,
          384.0
        ],
        [
          757.5,
          391.5
        ],
        [
          735.0,
          391.5
        ],
        [
          718.75,
          387.75
        ],
        [
          706.25,
          376.5
        ],
        [
          698.75,
          359.0
        ],
        [
          698.75,
          341.5
        ],
        [
          707.5,
          329.0
        ]
      ],
      "group_id": null,
      "shape_type": "polygon",
      "flags": {}
    },
    {
      "label": "cirtus4",
      "points": [
        [
          902.5,
          527.75
        ],
        [
          887.5,
          525.25
        ],
        [
          871.25,
          526.5
        ],
        [
          861.25,
          540.25
        ],
        [
          858.75,
          552.75
        ],
        [
          863.75,
          570.25
        ],
        [
          875.0,
          582.75
        ],
        [
          895.0,
          582.75
        ],
        [
          905.0,
          580.25
        ],
        [
          908.75,
          564.0
        ],
        [
          911.25,
          546.5
        ]
      ],
      "group_id": null,
      "shape_type": "polygon",
      "flags": {}
    },
    {
      "label": "cirtus5",
      "points": [
        [
          735.0,
          92.75
        ],
        [
          751.25,
          91.5
        ],
        [
          763.75,
          94.0
        ],
        [
          775.0,
          97.75
        ],
        [
          787.5,
          110.25
        ],
        [
          787.5,
          125.25
        ],
        [
          780.0,
          135.25
        ],
        [
          767.5,
          142.75
        ],
        [
          752.5,
          142.75
        ],
        [
          736.25,
          139.0
        ],
        [
          721.25,
          131.5
        ],
        [
          715.0,
          121.5
        ],
        [
          715.0,
          112.75
        ],
        [
          718.75,
          101.5
        ]
      ],
      "group_id": null,
      "shape_type": "polygon",
      "flags": {}
    },
    {
      "label": "cirtus6",
      "points": [
        [
          561.25,
          1.5
        ],
        [
          558.75,
          12.75
        ],
        [
          561.25,
          26.5
        ],
        [
          571.25,
          37.75
        ],
        [
          590.0,
          40.25
        ],
        [
          607.5,
          37.75
        ],
        [
          620.0,
          34.0
        ],
        [
          631.25,
          26.5
        ],
        [
          628.75,
          10.25
        ],
        [
          623.75,
          1.5
        ]
      ],
      "group_id": null,
      "shape_type": "polygon",
      "flags": {}
    }
  ],
  "imagePath": "ct449.jpg",
  "imageData": null,
  "imageHeight": 720,
  "imageWidth": 1280
}