{
  "version": "4.5.6",
  "flags": {},
  "shapes": [
    {
      "label": "cirtus1",
      "points": [
        [
          172.5,
          277.75
        ],
        [
          182.5,
          274.0
        ],
        [
          193.75,
          270.25
        ],
        [
          211.25,
          269.0
        ],
        [
          228.75,
          267.75
        ],
        [
          243.75,
          272.75
        ],
        [
          257.5,
          281.5
        ],
        [
          266.25,
          294.0
        ],
        [
          273.75,
          314.0
        ],
        [
          272.5,
          336.5
        ],
        [
          265.0,
          352.75
        ],
        [
          252.5,
          366.5
        ],
        [
          238.75,
          369.0
        ],
        [
          213.75,
          375.25
        ],
        [
          192.5,
          377.75
        ],
        [
          177.5,
          375.25
        ],
        [
          163.75,
          366.5
        ],
        [
          151.25,
          350.25
        ],
        [
          143.75,
          329.0
        ],
        [
          145.0,
          311.5
        ],
        [
          153.75,
          290.25
        ]
      ],
      "group_id": null,
      "shape_type": "polygon",
      "flags": {}
    },
    {
      "label": "cirtus2",
      "points": [
        [
          298.75,
          269.0
        ],
        [
          311.25,
          264.0
        ],
        [
          331.25,
          262.75
        ],
        [
          350.0,
          266.5
        ],
        [
          367.5,
          272.75
        ],
        [
          381.25,
          282.75
        ],
        [
          393.75,
          300.25
        ],
        [
          396.25,
          324.0
        ],
        [
          387.5,
          342.75
        ],
        [
          376.25,
          355.25
        ],
        [
          361.25,
          361.5
        ],
        [
          338.75,
          365.25
        ],
        [
          313.75,
          367.75
        ],
        [
          292.5,
          364.0
        ],
        [
          277.5,
          351.5
        ],
        [
          273.75,
          337.75
        ],
        [
          272.5,
          321.5
        ],
        [
          272.5,
          305.25
        ],
        [
          277.5,
          292.75
        ],
        [
          286.25,
          280.25
        ]
      ],
      "group_id": null,
      "shape_type": "polygon",
      "flags": {}
    },
    {
      "label": "cirtus3",
      "points": [
        [
          223.75,
          54.0
        ],
        [
          233.75,
          50.25
        ],
        [
          250.0,
          50.25
        ],
        [
          265.0,
          54.0
        ],
        [
          281.25,
          62.75
        ],
        [
          293.75,
          77.75
        ],
        [
          296.25,
          95.25
        ],
        [
          292.5,
          111.5
        ],
        [
          285.0,
          124.0
        ],
        [
          272.5,
          131.5
        ],
        [
          260.0,
          137.75
        ],
        [
          245.0,
          137.75
        ],
        [
          225.0,
          134.0
        ],
        [
          210.0,
          126.5
        ],
        [
          201.25,
          112.75
        ],
        [
          198.75,
          96.5
        ],
        [
          198.75,
          84.0
        ],
        [
          206.25,
          69.0
        ],
        [
          213.75,
          61.5
        ]
      ],
      "group_id": null,
      "shape_type": "polygon",
      "flags": {}
    },
    {
      "label": "cirtus4",
      "points": [
        [
          436.25,
          125.25
        ],
        [
          447.5,
          121.5
        ],
        [
          462.5,
          120.25
        ],
        [
          475.0,
          120.25
        ],
        [
          492.5,
          129.0
        ],
        [
          503.75,
          139.0
        ],
        [
          515.0,
          155.25
        ],
        [
          521.25,
          171.5
        ],
        [
          520.0,
          191.5
        ],
        [
          508.75,
          205.25
        ],
        [
          490.0,
          219.0
        ],
        [
          472.5,
          221.5
        ],
        [
          456.25,
          222.75
        ],
        [
          436.25,
          219.0
        ],
        [
          422.5,
          209.0
        ],
        [
          411.25,
          196.5
        ],
        [
          407.5,
          179.0
        ],
        [
          407.5,
          171.5
        ],
        [
          417.5,
          166.5
        ],
        [
          427.5,
          164.0
        ],
        [
          436.25,
          151.5
        ],
        [
          437.5,
          137.75
        ]
      ],
      "group_id": null,
      "shape_type": "polygon",
      "flags": {}
    },
    {
      "label": "cirtus5",
      "points": [
        [
          763.75,
          527.75
        ],
        [
          752.5,
          520.25
        ],
        [
          735.0,
          517.75
        ],
        [
          722.5,
          519.0
        ],
        [
          707.5,
          521.5
        ],
        [
          697.5,
          530.25
        ],
        [
          682.5,
          544.0
        ],
        [
          680.0,
          566.5
        ],
        [
          681.25,
          579.0
        ],
        [
          686.25,
          592.75
        ],
        [
          693.75,
          605.25
        ],
        [
          706.25,
          615.25
        ],
        [
          722.5,
          621.5
        ],
        [
          737.5,
          621.5
        ],
        [
          757.5,
          616.5
        ],
        [
          751.25,
          600.25
        ],
        [
          747.5,
          575.25
        ],
        [
          747.5,
          561.5
        ],
        [
          753.75,
          542.75
        ]
      ],
      "group_id": null,
      "shape_type": "polygon",
      "flags": {}
    },
    {
      "label": "cirtus6",
      "points": [
        [
          778.75,
          519.0
        ],
        [
          796.25,
          512.75
        ],
        [
          812.5,
          512.75
        ],
        [
          826.25,
          512.75
        ],
        [
          841.25,
          516.5
        ],
        [
          858.75,
          527.75
        ],
        [
          868.75,
          540.25
        ],
        [
          857.5,
          555.25
        ],
        [
          851.25,
          571.5
        ],
        [
          841.25,
          594.0
        ],
        [
          836.25,
          615.25
        ],
        [
          827.5,
          627.75
        ],
        [
          802.5,
          631.5
        ],
        [
          783.75,
          625.25
        ],
        [
          771.25,
          617.75
        ],
        [
          761.25,
          607.75
        ],
        [
          751.25,
          592.75
        ],
        [
          751.25,
          577.75
        ],
        [
          751.25,
          557.75
        ],
        [
          760.0,
          535.25
        ],
        [
          766.25,
          526.5
        ]
      ],
      "group_id": null,
      "shape_type": "polygon",
      "flags": {}
    },
    {
      "label": "cirtus7",
      "points": [
        [
          912.5,
          511.5
        ],
        [
          930.0,
          507.75
        ],
        [
          943.75,
          507.75
        ],
        [
          963.75,
          510.25
        ],
        [
          987.5,
          521.5
        ],
        [
          1005.0,
          534.0
        ],
        [
          1012.5,
          554.0
        ],
        [
          1017.5,
          571.5
        ],
        [
          1016.25,
          586.5
        ],
        [
          1012.5,
          605.25
        ],
        [
          1003.75,
          619.0
        ],
        [
          992.5,
          631.5
        ],
        [
          976.25,
          640.25
        ],
        [
          956.25,
          644.0
        ],
        [
          930.0,
          644.0
        ],
        [
          901.25,
          634.0
        ],
        [
          880.0,
          619.0
        ],
        [
          866.25,
          595.25
        ],
        [
          863.75,
          581.5
        ],
        [
          863.75,
          562.75
        ],
        [
          872.5,
          546.5
        ],
        [
          883.75,
          530.25
        ],
        [
          897.5,
          519.0
        ]
      ],
      "group_id": null,
      "shape_type": "polygon",
      "flags": {}
    },
    {
      "label": "cirtus8",
      "points": [
        [
          990.0,
          190.25
        ],
        [
          1008.75,
          186.5
        ],
        [
          1030.0,
          189.0
        ],
        [
          1051.25,
          196.5
        ],
        [
          1061.25,
          206.5
        ],
        [
          1071.25,
          222.75
        ],
        [
          1071.25,
          236.5
        ],
        [
          1071.25,
          252.75
        ],
        [
          1061.25,
          269.0
        ],
        [
          1048.75,
          279.0
        ],
        [
          1033.75,
          282.75
        ],
        [
          1008.75,
          284.0
        ],
        [
          987.5,
          279.0
        ],
        [
          975.0,
          275.25
        ],
        [
          961.25,
          255.25
        ],
        [
          957.5,
          241.5
        ],
        [
          957.5,
          222.75
        ],
        [
          962.5,
          209.0
        ],
        [
          976.25,
          197.75
        ]
      ],
      "group_id": null,
      "shape_type": "polygon",
      "flags": {}
    },
    {
      "label": "cirtus9",
      "points": [
        [
          1077.5,
          106.5
        ],
        [
          1088.75,
          106.5
        ],
        [
          1103.75,
          110.25
        ],
        [
          1113.75,
          116.5
        ],
        [
          1126.25,
          127.75
        ],
        [
          1135.0,
          145.25
        ],
        [
          1131.25,
          167.75
        ],
        [
          1118.75,
          181.5
        ],
        [
          1101.25,
          192.75
        ],
        [
          1081.25,
          197.75
        ],
        [
          1061.25,
          196.5
        ],
        [
          1046.25,
          187.75
        ],
        [
          1033.75,
          167.75
        ],
        [
          1033.75,
          147.75
        ],
        [
          1040.0,
          130.25
        ],
        [
          1051.25,
          117.75
        ],
        [
          1062.5,
          110.25
        ]
      ],
      "group_id": null,
      "shape_type": "polygon",
      "flags": {}
    },
    {
      "label": "cirtus10",
      "points": [
        [
          1068.75,
          107.75
        ],
        [
          1066.25,
          96.5
        ],
        [
          1073.75,
          80.25
        ],
        [
          1082.5,
          66.5
        ],
        [
          1097.5,
          57.75
        ],
        [
          1111.25,
          52.75
        ],
        [
          1131.25,
          55.25
        ],
        [
          1153.75,
          62.75
        ],
        [
          1163.75,
          71.5
        ],
        [
          1170.0,
          89.0
        ],
        [
          1172.5,
          104.0
        ],
        [
          1168.75,
          121.5
        ],
        [
          1156.25,
          131.5
        ],
        [
          1135.0,
          137.75
        ],
        [
          1125.0,
          124.0
        ],
        [
          1110.0,
          116.5
        ],
        [
          1092.5,
          109.0
        ]
      ],
      "group_id": null,
      "shape_type": "polygon",
      "flags": {}
    }
  ],
  "imagePath": "ct54.jpg",
  "imageData": null,
  "imageHeight": 720,
  "imageWidth": 1280
}