{
  "version": "4.5.6",
  "flags": {},
  "shapes": [
    {
      "label": "cirtus1",
      "points": [
        [
          863.6326530612245,
          400.7551020408163
        ],
        [
          848.3265306122448,
          397.6938775510204
        ],
        [
          838.1224489795918,
          393.61224489795916
        ],
        [
          834.0408163265306,
          385.44897959183675
        ],
        [
          835.0612244897959,
          374.2244897959184
        ],
        [
          841.1836734693877,
          359.9387755102041
        ],
        [
          854.4489795918367,
          349.734693877551
        ],
        [
          869.7551020408164,
          344.63265306122446
        ],
        [
          886.0816326530612,
          347.6938775510204
        ],
        [
          903.4285714285714,
          353.81632653061223
        ],
        [
          911.5918367346939,
          365.0408163265306
        ],
        [
          911.5918367346939,
          380.3469387755102
        ],
        [
          905.469387755102,
          391.57142857142856
        ],
        [
          893.2244897959183,
          397.6938775510204
        ],
        [
          876.8979591836735,
          400.7551020408163
        ]
      ],
      "group_id": null,
      "shape_type": "polygon",
      "flags": {}
    },
    {
      "label": "cirtus4",
      "points": [
        [
          1194.2448979591836,
          294.63265306122446
        ],
        [
          1175.8775510204082,
          299.734693877551
        ],
        [
          1158.5306122448978,
          299.734693877551
        ],
        [
          1144.2448979591836,
          295.65306122448976
        ],
        [
          1132.0,
          286.46938775510205
        ],
        [
          1125.8775510204082,
          271.1632653061224
        ],
        [
          1127.9183673469388,
          256.87755102040813
        ],
        [
          1139.142857142857,
          241.57142857142856
        ],
        [
          1158.5306122448978,
          235.44897959183675
        ],
        [
          1183.0204081632653,
          232.38775510204084
        ],
        [
          1198.3265306122448,
          244.63265306122446
        ],
        [
          1206.4897959183672,
          263.0
        ],
        [
          1208.5306122448978,
          278.3061224489796
        ]
      ],
      "group_id": null,
      "shape_type": "polygon",
      "flags": {}
    },
    {
      "label": "cirtus5",
      "points": [
        [
          485.0612244897959,
          238.51020408163265
        ],
        [
          471.79591836734687,
          232.38775510204084
        ],
        [
          460.57142857142856,
          217.0816326530612
        ],
        [
          463.63265306122446,
          200.75510204081627
        ],
        [
          475.8775510204082,
          195.65306122448976
        ],
        [
          493.2244897959183,
          190.55102040816325
        ],
        [
          509.55102040816325,
          190.55102040816325
        ],
        [
          521.7959183673469,
          202.79591836734699
        ],
        [
          521.7959183673469,
          220.1428571428571
        ],
        [
          514.6530612244898,
          231.36734693877554
        ]
      ],
      "group_id": null,
      "shape_type": "polygon",
      "flags": {}
    },
    {
      "label": "cirtus8",
      "points": [
        [
          359.55102040816325,
          461.9795918367347
        ],
        [
          345.2653061224489,
          455.85714285714283
        ],
        [
          335.0612244897959,
          441.57142857142856
        ],
        [
          337.1020408163265,
          422.18367346938777
        ],
        [
          347.3061224489795,
          416.0612244897959
        ],
        [
          366.69387755102036,
          411.9795918367347
        ],
        [
          386.0816326530612,
          416.0612244897959
        ],
        [
          394.2448979591836,
          429.3265306122449
        ],
        [
          395.2653061224489,
          446.6734693877551
        ],
        [
          380.9795918367347,
          456.87755102040813
        ]
      ],
      "group_id": null,
      "shape_type": "polygon",
      "flags": {}
    },
    {
      "label": "cirtus9",
      "points": [
        [
          383.0204081632653,
          496.6734693877551
        ],
        [
          370.77551020408157,
          488.51020408163265
        ],
        [
          367.71428571428567,
          472.18367346938777
        ],
        [
          373.8367346938776,
          458.9183673469388
        ],
        [
          388.1224489795918,
          449.734693877551
        ],
        [
          403.42857142857144,
          450.7551020408163
        ],
        [
          420.77551020408157,
          457.89795918367344
        ],
        [
          426.8979591836735,
          468.1020408163265
        ],
        [
          425.8775510204082,
          482.3877551020408
        ],
        [
          414.65306122448976,
          495.6530612244898
        ],
        [
          400.36734693877554,
          500.7551020408163
        ]
      ],
      "group_id": null,
      "shape_type": "polygon",
      "flags": {}
    },
    {
      "label": "cirtus2",
      "points": [
        [
          782.5,
          369.75
        ],
        [
          771.25,
          362.25
        ],
        [
          767.5,
          346.0
        ],
        [
          771.25,
          334.75
        ],
        [
          783.75,
          326.0
        ],
        [
          800.0,
          322.25
        ],
        [
          815.0,
          322.25
        ],
        [
          823.75,
          327.25
        ],
        [
          827.5,
          341.0
        ],
        [
          822.5,
          357.25
        ],
        [
          810.0,
          363.5
        ],
        [
          798.75,
          371.0
        ]
      ],
      "group_id": null,
      "shape_type": "polygon",
      "flags": {}
    },
    {
      "label": "cirtus3",
      "points": [
        [
          765.0,
          336.0
        ],
        [
          751.25,
          331.0
        ],
        [
          743.75,
          321.0
        ],
        [
          743.75,
          309.75
        ],
        [
          746.25,
          301.0
        ],
        [
          756.25,
          291.0
        ],
        [
          770.0,
          284.75
        ],
        [
          786.25,
          286.0
        ],
        [
          798.75,
          291.0
        ],
        [
          801.25,
          299.75
        ],
        [
          800.0,
          311.0
        ],
        [
          790.0,
          319.75
        ],
        [
          782.5,
          324.75
        ]
      ],
      "group_id": null,
      "shape_type": "polygon",
      "flags": {}
    },
    {
      "label": "cirtus6",
      "points": [
        [
          567.5,
          386.0
        ],
        [
          552.5,
          377.25
        ],
        [
          543.75,
          367.25
        ],
        [
          542.5,
          353.5
        ],
        [
          551.25,
          339.75
        ],
        [
          565.0,
          334.75
        ],
        [
          581.25,
          333.5
        ],
        [
          596.25,
          337.25
        ],
        [
          605.0,
          349.75
        ],
        [
          606.25,
          359.75
        ],
        [
          598.75,
          376.0
        ],
        [
          582.5,
          384.75
        ]
      ],
      "group_id": null,
      "shape_type": "polygon",
      "flags": {}
    },
    {
      "label": "cirtus7",
      "points": [
        [
          505.0,
          363.5
        ],
        [
          497.5,
          358.5
        ],
        [
          497.5,
          346.0
        ],
        [
          498.75,
          334.75
        ],
        [
          513.75,
          323.5
        ],
        [
          527.5,
          318.5
        ],
        [
          543.75,
          322.25
        ],
        [
          556.25,
          331.0
        ],
        [
          556.25,
          346.0
        ],
        [
          547.5,
          357.25
        ],
        [
          526.25,
          356.0
        ]
      ],
      "group_id": null,
      "shape_type": "polygon",
      "flags": {}
    }
  ],
  "imagePath": "hf289.jpg",
  "imageData": null,
  "imageHeight": 720,
  "imageWidth": 1280
}