{
  "version": "4.5.6",
  "flags": {},
  "shapes": [
    {
      "label": "cirtus1",
      "points": [
        [
          1278.75,
          637.25
        ],
        [
          1262.5,
          642.25
        ],
        [
          1243.75,
          642.25
        ],
        [
          1225.0,
          634.75
        ],
        [
          1217.5,
          618.5
        ],
        [
          1216.25,
          603.5
        ],
        [
          1223.75,
          589.75
        ],
        [
          1242.5,
          577.25
        ],
        [
          1263.75,
          574.75
        ],
        [
          1277.5,
          582.25
        ]
      ],
      "group_id": null,
      "shape_type": "polygon",
      "flags": {}
    },
    {
      "label": "cirtus2",
      "points": [
        [
          1178.75,
          632.25
        ],
        [
          1162.5,
          629.75
        ],
        [
          1143.75,
          616.0
        ],
        [
          1145.0,
          607.25
        ],
        [
          1155.0,
          601.0
        ],
        [
          1155.0,
          584.75
        ],
        [
          1163.75,
          573.5
        ],
        [
          1180.0,
          571.0
        ],
        [
          1202.5,
          578.5
        ],
        [
          1215.0,
          593.5
        ],
        [
          1216.25,
          604.75
        ],
        [
          1208.75,
          618.5
        ],
        [
          1196.25,
          627.25
        ]
      ],
      "group_id": null,
      "shape_type": "polygon",
      "flags": {}
    },
    {
      "label": "cirtus3",
      "points": [
        [
          456.25,
          477.25
        ],
        [
          446.25,
          466.0
        ],
        [
          445.0,
          446.0
        ],
        [
          453.75,
          431.0
        ],
        [
          470.0,
          426.0
        ],
        [
          486.25,
          422.25
        ],
        [
          511.25,
          424.75
        ],
        [
          518.75,
          432.25
        ],
        [
          508.75,
          449.75
        ],
        [
          495.0,
          471.0
        ],
        [
          480.0,
          476.0
        ]
      ],
      "group_id": null,
      "shape_type": "polygon",
      "flags": {}
    },
    {
      "label": "cirtus4",
      "points": [
        [
          685.0,
          546.0
        ],
        [
          670.0,
          548.5
        ],
        [
          655.0,
          547.25
        ],
        [
          645.0,
          543.5
        ],
        [
          642.5,
          534.75
        ],
        [
          642.5,
          526.0
        ],
        [
          646.25,
          516.0
        ],
        [
          656.25,
          512.25
        ],
        [
          667.5,
          511.0
        ],
        [
          676.25,
          512.25
        ],
        [
          687.5,
          517.25
        ],
        [
          695.0,
          523.5
        ],
        [
          696.25,
          537.25
        ]
      ],
      "group_id": null,
      "shape_type": "polygon",
      "flags": {}
    },
    {
      "label": "cirtus5",
      "points": [
        [
          1260.0,
          1.0
        ],
        [
          1266.25,
          13.5
        ],
        [
          1265.0,
          31.0
        ],
        [
          1257.5,
          43.5
        ],
        [
          1241.25,
          52.25
        ],
        [
          1223.75,
          58.5
        ],
        [
          1201.25,
          54.75
        ],
        [
          1187.5,
          51.0
        ],
        [
          1175.0,
          44.75
        ],
        [
          1173.75,
          24.75
        ],
        [
          1168.75,
          13.5
        ],
        [
          1176,
          1
        ]
      ],
      "group_id": null,
      "shape_type": "polygon",
      "flags": {}
    }
  ],
  "imagePath": "hf343.jpg",
  "imageData": null,
  "imageHeight": 720,
  "imageWidth": 1280
}