{
  "version": "4.5.6",
  "flags": {},
  "shapes": [
    {
      "label": "cirtus1",
      "points": [
        [
          813.75,
          476.0
        ],
        [
          800.0,
          481.0
        ],
        [
          786.25,
          482.25
        ],
        [
          772.5,
          473.5
        ],
        [
          767.5,
          466.0
        ],
        [
          767.5,
          452.25
        ],
        [
          775.0,
          439.75
        ],
        [
          786.25,
          437.25
        ],
        [
          805.0,
          434.75
        ],
        [
          817.5,
          443.5
        ],
        [
          822.5,
          458.5
        ]
      ],
      "group_id": null,
      "shape_type": "polygon",
      "flags": {}
    },
    {
      "label": "cirtus2",
      "points": [
        [
          771.25,
          219.75
        ],
        [
          781.25,
          222.25
        ],
        [
          795.0,
          217.25
        ],
        [
          807.5,
          216.0
        ],
        [
          817.5,
          202.25
        ],
        [
          821.25,
          189.75
        ],
        [
          817.5,
          179.75
        ],
        [
          796.25,
          167.25
        ],
        [
          777.5,
          172.25
        ],
        [
          761.25,
          178.5
        ],
        [
          777.5,
          194.75
        ],
        [
          756.25,
          188.5
        ],
        [
          755.0,
          203.5
        ]
      ],
      "group_id": null,
      "shape_type": "polygon",
      "flags": {}
    },
    {
      "label": "cirtus3",
      "points": [
        [
          408.75,
          484.75
        ],
        [
          398.75,
          489.75
        ],
        [
          382.5,
          491.0
        ],
        [
          368.75,
          482.25
        ],
        [
          363.75,
          467.25
        ],
        [
          375.0,
          458.5
        ],
        [
          388.75,
          456.0
        ],
        [
          407.5,
          462.25
        ]
      ],
      "group_id": null,
      "shape_type": "polygon",
      "flags": {}
    },
    {
      "label": "cirtus4",
      "points": [
        [
          386.25,
          341.0
        ],
        [
          371.25,
          342.25
        ],
        [
          356.25,
          337.25
        ],
        [
          348.75,
          319.75
        ],
        [
          348.75,
          304.75
        ],
        [
          360.0,
          296.0
        ],
        [
          372.5,
          292.25
        ],
        [
          388.75,
          294.75
        ],
        [
          402.5,
          302.25
        ],
        [
          411.25,
          313.5
        ],
        [
          411.25,
          331.0
        ],
        [
          401.25,
          339.75
        ]
      ],
      "group_id": null,
      "shape_type": "polygon",
      "flags": {}
    },
    {
      "label": "cirtus5",
      "points": [
        [
          878.75,
          598.5
        ],
        [
          872.5,
          604.75
        ],
        [
          858.75,
          604.75
        ],
        [
          841.25,
          596.0
        ],
        [
          835.0,
          584.75
        ],
        [
          842.5,
          574.75
        ],
        [
          856.25,
          573.5
        ],
        [
          870.0,
          576.0
        ],
        [
          882.5,
          583.5
        ]
      ],
      "group_id": null,
      "shape_type": "polygon",
      "flags": {}
    }
  ],
  "imagePath": "hf405.jpg",
  "imageData": null,
  "imageHeight": 720,
  "imageWidth": 1280
}