{
  "version": "4.5.6",
  "flags": {},
  "shapes": [
    {
      "label": "cirtus1",
      "points": [
        [
          928.75,
          447.25
        ],
        [
          918.75,
          453.5
        ],
        [
          908.75,
          454.75
        ],
        [
          897.5,
          451.0
        ],
        [
          891.25,
          441.0
        ],
        [
          886.25,
          428.5
        ],
        [
          885.0,
          411.0
        ],
        [
          892.5,
          401.0
        ],
        [
          910.0,
          399.75
        ],
        [
          923.75,
          404.75
        ],
        [
          937.5,
          411.0
        ],
        [
          943.75,
          418.5
        ],
        [
          938.75,
          434.75
        ]
      ],
      "group_id": null,
      "shape_type": "polygon",
      "flags": {}
    },
    {
      "label": "cirtus2",
      "points": [
        [
          628.75,
          444.75
        ],
        [
          615.0,
          446.0
        ],
        [
          601.25,
          446.0
        ],
        [
          585.0,
          437.25
        ],
        [
          575.0,
          424.75
        ],
        [
          571.25,
          414.75
        ],
        [
          573.75,
          403.5
        ],
        [
          586.25,
          393.5
        ],
        [
          601.25,
          393.5
        ],
        [
          610.0,
          388.5
        ],
        [
          626.25,
          388.5
        ],
        [
          637.5,
          392.25
        ],
        [
          653.75,
          401.0
        ],
        [
          652.5,
          414.75
        ],
        [
          647.5,
          433.5
        ]
      ],
      "group_id": null,
      "shape_type": "polygon",
      "flags": {}
    },
    {
      "label": "cirtus3",
      "points": [
        [
          387.5,
          372.25
        ],
        [
          372.5,
          377.25
        ],
        [
          357.5,
          377.25
        ],
        [
          345.0,
          368.5
        ],
        [
          337.5,
          361.0
        ],
        [
          336.25,
          351.0
        ],
        [
          341.25,
          341.0
        ],
        [
          352.5,
          333.5
        ],
        [
          365.0,
          332.25
        ],
        [
          377.5,
          332.25
        ],
        [
          388.75,
          341.0
        ],
        [
          392.5,
          353.5
        ],
        [
          395.0,
          362.25
        ]
      ],
      "group_id": null,
      "shape_type": "polygon",
      "flags": {}
    },
    {
      "label": "cirtus4",
      "points": [
        [
          507.5,
          97.25
        ],
        [
          522.5,
          98.5
        ],
        [
          533.75,
          91.0
        ],
        [
          542.5,
          82.25
        ],
        [
          548.75,
          68.5
        ],
        [
          542.5,
          53.5
        ],
        [
          533.75,
          43.5
        ],
        [
          520.0,
          41.0
        ],
        [
          502.5,
          42.25
        ],
        [
          491.25,
          44.75
        ],
        [
          480.0,
          48.5
        ],
        [
          468.75,
          57.25
        ],
        [
          488.75,
          63.5
        ],
        [
          476.25,
          67.25
        ],
        [
          476.25,
          81.0
        ],
        [
          486.25,
          89.75
        ],
        [
          495.0,
          94.75
        ]
      ],
      "group_id": null,
      "shape_type": "polygon",
      "flags": {}
    },
    {
      "label": "cirtus5",
      "points": [
        [
          1025.0,
          328.5
        ],
        [
          1030.0,
          319.75
        ],
        [
          1032.5,
          307.25
        ],
        [
          1025.0,
          297.25
        ],
        [
          1013.75,
          289.75
        ],
        [
          1002.5,
          289.75
        ],
        [
          991.25,
          293.5
        ],
        [
          983.75,
          298.5
        ],
        [
          988.75,
          313.5
        ],
        [
          1012.5,
          329.75
        ]
      ],
      "group_id": null,
      "shape_type": "polygon",
      "flags": {}
    }
  ],
  "imagePath": "hf470.jpg",
  "imageData": null,
  "imageHeight": 720,
  "imageWidth": 1280
}