{
  "version": "4.5.6",
  "flags": {},
  "shapes": [
    {
      "label": "cirtus1",
      "points": [
        [
          416.36734693877554,
          319.2448979591837
        ],
        [
          431.6734693877551,
          322.3061224489796
        ],
        [
          441.8775510204082,
          326.38775510204084
        ],
        [
          445.9591836734694,
          334.55102040816325
        ],
        [
          444.9387755102041,
          345.7755102040816
        ],
        [
          438.81632653061223,
          360.0612244897959
        ],
        [
          425.55102040816325,
          370.265306122449
        ],
        [
          410.2448979591837,
          375.36734693877554
        ],
        [
          393.9183673469388,
          372.3061224489796
        ],
        [
          376.57142857142856,
          366.18367346938777
        ],
        [
          368.40816326530614,
          354.9591836734694
        ],
        [
          368.40816326530614,
          339.6530612244898
        ],
        [
          374.53061224489795,
          328.42857142857144
        ],
        [
          386.7755102040816,
          322.3061224489796
        ],
        [
          403.10204081632656,
          319.2448979591837
        ]
      ],
      "group_id": null,
      "shape_type": "polygon",
      "flags": {}
    },
    {
      "label": "cirtus4",
      "points": [
        [
          85.75510204081633,
          425.36734693877554
        ],
        [
          104.12244897959184,
          420.265306122449
        ],
        [
          121.46938775510205,
          420.265306122449
        ],
        [
          135.75510204081633,
          424.34693877551024
        ],
        [
          148.0,
          433.53061224489795
        ],
        [
          154.12244897959184,
          448.8367346938776
        ],
        [
          152.08163265306123,
          463.12244897959187
        ],
        [
          140.85714285714286,
          478.42857142857144
        ],
        [
          121.46938775510205,
          484.55102040816325
        ],
        [
          96.9795918367347,
          487.61224489795916
        ],
        [
          81.6734693877551,
          475.36734693877554
        ],
        [
          73.51020408163265,
          457.0
        ],
        [
          71.46938775510205,
          441.6938775510204
        ]
      ],
      "group_id": null,
      "shape_type": "polygon",
      "flags": {}
    },
    {
      "label": "cirtus5",
      "points": [
        [
          794.9387755102041,
          481.48979591836735
        ],
        [
          808.2040816326531,
          487.61224489795916
        ],
        [
          819.4285714285714,
          502.9183673469388
        ],
        [
          816.3673469387755,
          519.2448979591837
        ],
        [
          804.1224489795918,
          524.3469387755102
        ],
        [
          786.7755102040817,
          529.4489795918367
        ],
        [
          770.4489795918367,
          529.4489795918367
        ],
        [
          758.2040816326531,
          517.204081632653
        ],
        [
          758.2040816326531,
          499.8571428571429
        ],
        [
          765.3469387755102,
          488.63265306122446
        ]
      ],
      "group_id": null,
      "shape_type": "polygon",
      "flags": {}
    },
    {
      "label": "cirtus8",
      "points": [
        [
          920.4489795918367,
          258.0204081632653
        ],
        [
          934.7346938775511,
          264.14285714285717
        ],
        [
          944.9387755102041,
          278.42857142857144
        ],
        [
          942.8979591836735,
          297.81632653061223
        ],
        [
          932.6938775510205,
          303.9387755102041
        ],
        [
          913.3061224489796,
          308.0204081632653
        ],
        [
          893.9183673469388,
          303.9387755102041
        ],
        [
          885.7551020408164,
          290.6734693877551
        ],
        [
          884.7346938775511,
          273.3265306122449
        ],
        [
          899.0204081632653,
          263.12244897959187
        ]
      ],
      "group_id": null,
      "shape_type": "polygon",
      "flags": {}
    },
    {
      "label": "cirtus9",
      "points": [
        [
          896.9795918367347,
          223.32653061224488
        ],
        [
          909.2244897959184,
          231.48979591836735
        ],
        [
          912.2857142857143,
          247.81632653061223
        ],
        [
          906.1632653061224,
          261.0816326530612
        ],
        [
          891.8775510204082,
          270.265306122449
        ],
        [
          876.5714285714286,
          269.2448979591837
        ],
        [
          859.2244897959184,
          262.10204081632656
        ],
        [
          853.1020408163265,
          251.8979591836735
        ],
        [
          854.1224489795918,
          237.61224489795921
        ],
        [
          865.3469387755102,
          224.34693877551018
        ],
        [
          879.6326530612245,
          219.24489795918367
        ]
      ],
      "group_id": null,
      "shape_type": "polygon",
      "flags": {}
    },
    {
      "label": "cirtus2",
      "points": [
        [
          497.5,
          350.25
        ],
        [
          508.75,
          357.75
        ],
        [
          512.5,
          374.0
        ],
        [
          508.75,
          385.25
        ],
        [
          496.25,
          394.0
        ],
        [
          480.0,
          397.75
        ],
        [
          465.0,
          397.75
        ],
        [
          456.25,
          392.75
        ],
        [
          452.5,
          379.0
        ],
        [
          457.5,
          362.75
        ],
        [
          470.0,
          356.5
        ],
        [
          481.25,
          349.0
        ]
      ],
      "group_id": null,
      "shape_type": "polygon",
      "flags": {}
    },
    {
      "label": "cirtus3",
      "points": [
        [
          515.0,
          384.0
        ],
        [
          528.75,
          389.0
        ],
        [
          536.25,
          399.0
        ],
        [
          536.25,
          410.25
        ],
        [
          533.75,
          419.0
        ],
        [
          523.75,
          429.0
        ],
        [
          510.0,
          435.25
        ],
        [
          493.75,
          434.0
        ],
        [
          481.25,
          429.0
        ],
        [
          478.75,
          420.25
        ],
        [
          480.0,
          409.0
        ],
        [
          490.0,
          400.25
        ],
        [
          497.5,
          395.25
        ]
      ],
      "group_id": null,
      "shape_type": "polygon",
      "flags": {}
    },
    {
      "label": "cirtus6",
      "points": [
        [
          712.5,
          334.0
        ],
        [
          727.5,
          342.75
        ],
        [
          736.25,
          352.75
        ],
        [
          737.5,
          366.5
        ],
        [
          728.75,
          380.25
        ],
        [
          715.0,
          385.25
        ],
        [
          698.75,
          386.5
        ],
        [
          683.75,
          382.75
        ],
        [
          675.0,
          370.25
        ],
        [
          673.75,
          360.25
        ],
        [
          681.25,
          344.0
        ],
        [
          697.5,
          335.25
        ]
      ],
      "group_id": null,
      "shape_type": "polygon",
      "flags": {}
    },
    {
      "label": "cirtus7",
      "points": [
        [
          775.0,
          356.5
        ],
        [
          782.5,
          361.5
        ],
        [
          782.5,
          374.0
        ],
        [
          781.25,
          385.25
        ],
        [
          766.25,
          396.5
        ],
        [
          752.5,
          401.5
        ],
        [
          736.25,
          397.75
        ],
        [
          723.75,
          389.0
        ],
        [
          723.75,
          374.0
        ],
        [
          732.5,
          362.75
        ],
        [
          753.75,
          364.0
        ]
      ],
      "group_id": null,
      "shape_type": "polygon",
      "flags": {}
    }
  ],
  "imagePath": "ct289.jpg",
  "imageData": null,
  "imageHeight": 720,
  "imageWidth": 1280
}