{
  "version": "4.5.6",
  "flags": {},
  "shapes": [
    {
      "label": "cirtus1",
      "points": [
        [
          518.75,
          492.75
        ],
        [
          520.0,
          477.75
        ],
        [
          525.0,
          462.75
        ],
        [
          533.75,
          447.75
        ],
        [
          551.25,
          439.0
        ],
        [
          572.5,
          434.0
        ],
        [
          591.25,
          435.25
        ],
        [
          607.5,
          441.5
        ],
        [
          623.75,
          454.0
        ],
        [
          637.5,
          466.5
        ],
        [
          647.5,
          481.5
        ],
        [
          647.5,
          494.0
        ],
        [
          643.75,
          510.25
        ],
        [
          632.5,
          526.5
        ],
        [
          627.5,
          535.25
        ],
        [
          597.5,
          535.25
        ],
        [
          575.0,
          542.75
        ],
        [
          552.5,
          540.25
        ],
        [
          536.25,
          532.75
        ],
        [
          526.25,
          520.25
        ],
        [
          520.0,
          507.75
        ]
      ],
      "group_id": null,
      "shape_type": "polygon",
      "flags": {}
    },
    {
      "label": "cirtus2",
      "points": [
        [
          375.0,
          266.5
        ],
        [
          358.75,
          260.25
        ],
        [
          345.0,
          254.0
        ],
        [
          336.25,
          241.5
        ],
        [
          335.0,
          224.0
        ],
        [
          338.75,
          210.25
        ],
        [
          346.25,
          197.75
        ],
        [
          360.0,
          189.0
        ],
        [
          375.0,
          181.5
        ],
        [
          387.5,
          181.5
        ],
        [
          388.75,
          204.0
        ],
        [
          392.5,
          224.0
        ],
        [
          405.0,
          241.5
        ],
        [
          415.0,
          257.75
        ],
        [
          398.75,
          266.5
        ]
      ],
      "group_id": null,
      "shape_type": "polygon",
      "flags": {}
    },
    {
      "label": "cirtus3",
      "points": [
        [
          613.75,
          320.25
        ],
        [
          601.25,
          325.25
        ],
        [
          591.25,
          334.0
        ],
        [
          586.25,
          346.5
        ],
        [
          583.75,
          367.75
        ],
        [
          593.75,
          369.0
        ],
        [
          601.25,
          377.75
        ],
        [
          597.5,
          390.25
        ],
        [
          610.0,
          401.5
        ],
        [
          628.75,
          409.0
        ],
        [
          647.5,
          406.5
        ],
        [
          666.25,
          396.5
        ],
        [
          656.25,
          381.5
        ],
        [
          640.0,
          356.5
        ],
        [
          630.0,
          340.25
        ]
      ],
      "group_id": null,
      "shape_type": "polygon",
      "flags": {}
    }
  ],
  "imagePath": "ct74.jpg",
  "imageData": null,
  "imageHeight": 720,
  "imageWidth": 1280
}