{
  "version": "4.5.6",
  "flags": {},
  "shapes": [
    {
      "label": "cirtus1",
      "points": [
        [
          923.75,
          318.5
        ],
        [
          917.5,
          327.25
        ],
        [
          911.25,
          336.0
        ],
        [
          897.5,
          339.75
        ],
        [
          872.5,
          339.75
        ],
        [
          856.25,
          333.5
        ],
        [
          847.5,
          322.25
        ],
        [
          845.0,
          303.5
        ],
        [
          856.25,
          286.0
        ],
        [
          873.75,
          282.25
        ],
        [
          891.25,
          282.25
        ],
        [
          905.0,
          288.5
        ],
        [
          918.75,
          299.75
        ]
      ],
      "group_id": null,
      "shape_type": "polygon",
      "flags": {}
    },
    {
      "label": "cirtus2",
      "points": [
        [
          1021.25,
          302.25
        ],
        [
          1011.25,
          303.5
        ],
        [
          995.0,
          306.0
        ],
        [
          981.25,
          296.0
        ],
        [
          975.0,
          284.75
        ],
        [
          976.25,
          268.5
        ],
        [
          983.75,
          258.5
        ],
        [
          996.25,
          256.0
        ],
        [
          1007.5,
          256.0
        ],
        [
          1022.5,
          261.0
        ],
        [
          1033.75,
          269.75
        ],
        [
          1037.5,
          279.75
        ]
      ],
      "group_id": null,
      "shape_type": "polygon",
      "flags": {}
    },
    {
      "label": "cirtus3",
      "points": [
        [
          1203.75,
          193.5
        ],
        [
          1196.25,
          201.0
        ],
        [
          1182.5,
          206.0
        ],
        [
          1170.0,
          202.25
        ],
        [
          1157.5,
          194.75
        ],
        [
          1152.5,
          178.5
        ],
        [
          1160.0,
          166.0
        ],
        [
          1173.75,
          161.0
        ],
        [
          1188.75,
          159.75
        ],
        [
          1203.75,
          164.75
        ],
        [
          1212.5,
          182.25
        ]
      ],
      "group_id": null,
      "shape_type": "polygon",
      "flags": {}
    },
    {
      "label": "cirtus4",
      "points": [
        [
          898.75,
          117.25
        ],
        [
          882.5,
          117.25
        ],
        [
          867.5,
          109.75
        ],
        [
          865.0,
          97.25
        ],
        [
          867.5,
          84.75
        ],
        [
          873.75,
          77.25
        ],
        [
          890.0,
          69.75
        ],
        [
          910.0,
          71.0
        ],
        [
          923.75,
          79.75
        ],
        [
          930.0,
          91.0
        ],
        [
          925.0,
          103.5
        ],
        [
          913.75,
          113.5
        ]
      ],
      "group_id": null,
      "shape_type": "polygon",
      "flags": {}
    },
    {
      "label": "cirtus5",
      "points": [
        [
          1080.0,
          478.5
        ],
        [
          1095.0,
          476.0
        ],
        [
          1107.5,
          471.0
        ],
        [
          1117.5,
          456.0
        ],
        [
          1118.75,
          439.75
        ],
        [
          1111.25,
          428.5
        ],
        [
          1095.0,
          422.25
        ],
        [
          1082.5,
          419.75
        ],
        [
          1063.75,
          426.0
        ],
        [
          1056.25,
          431.0
        ],
        [
          1051.25,
          443.5
        ],
        [
          1056.25,
          459.75
        ],
        [
          1070.0,
          458.5
        ],
        [
          1078.75,
          463.5
        ]
      ],
      "group_id": null,
      "shape_type": "polygon",
      "flags": {}
    },
    {
      "label": "cirtus6",
      "points": [
        [
          1145.0,
          409.75
        ],
        [
          1143.75,
          426.0
        ],
        [
          1128.75,
          433.5
        ],
        [
          1115.0,
          433.5
        ],
        [
          1105.0,
          426.0
        ],
        [
          1098.75,
          414.75
        ],
        [
          1102.5,
          403.5
        ],
        [
          1110.0,
          403.5
        ],
        [
          1125.0,
          398.5
        ],
        [
          1137.5,
          393.5
        ]
      ],
      "group_id": null,
      "shape_type": "polygon",
      "flags": {}
    },
    {
      "label": "cirtus7",
      "points": [
        [
          915.0,
          557.25
        ],
        [
          923.75,
          551.0
        ],
        [
          928.75,
          538.5
        ],
        [
          925.0,
          521.0
        ],
        [
          916.25,
          507.25
        ],
        [
          902.5,
          504.75
        ],
        [
          885.0,
          502.25
        ],
        [
          867.5,
          508.5
        ],
        [
          851.25,
          516.0
        ],
        [
          848.75,
          528.5
        ],
        [
          851.25,
          546.0
        ],
        [
          863.75,
          561.0
        ],
        [
          873.75,
          562.25
        ],
        [
          880.0,
          548.5
        ],
        [
          890.0,
          543.5
        ],
        [
          901.25,
          543.5
        ]
      ],
      "group_id": null,
      "shape_type": "polygon",
      "flags": {}
    },
    {
      "label": "cirtus8",
      "points": [
        [
          822.5,
          618.5
        ],
        [
          823.75,
          606.0
        ],
        [
          817.5,
          589.75
        ],
        [
          807.5,
          576.0
        ],
        [
          786.25,
          571.0
        ],
        [
          772.5,
          571.0
        ],
        [
          761.25,
          578.5
        ],
        [
          756.25,
          588.5
        ],
        [
          755.0,
          602.25
        ],
        [
          766.25,
          606.0
        ],
        [
          786.25,
          613.5
        ],
        [
          806.25,
          616.0
        ]
      ],
      "group_id": null,
      "shape_type": "polygon",
      "flags": {}
    },
    {
      "label": "cirtus9",
      "points": [
        [
          465.0,
          634.75
        ],
        [
          451.25,
          633.5
        ],
        [
          433.75,
          627.25
        ],
        [
          426.25,
          618.5
        ],
        [
          426.25,
          604.75
        ],
        [
          431.25,
          589.75
        ],
        [
          442.5,
          579.75
        ],
        [
          462.5,
          577.25
        ],
        [
          476.25,
          578.5
        ],
        [
          491.25,
          588.5
        ],
        [
          497.5,
          601.0
        ],
        [
          497.5,
          616.0
        ],
        [
          490.0,
          624.75
        ],
        [
          478.75,
          632.25
        ]
      ],
      "group_id": null,
      "shape_type": "polygon",
      "flags": {}
    },
    {
      "label": "cirtus10",
      "points": [
        [
          716.25,
          668.5
        ],
        [
          725.0,
          678.5
        ],
        [
          725.0,
          691.0
        ],
        [
          707.5,
          701.0
        ],
        [
          693.75,
          706.0
        ],
        [
          681.25,
          703.5
        ],
        [
          677.5,
          697.25
        ],
        [
          663.75,
          688.5
        ],
        [
          656.25,
          681.0
        ],
        [
          667.5,
          667.25
        ],
        [
          686.25,
          666.0
        ],
        [
          703.75,
          668.5
        ]
      ],
      "group_id": null,
      "shape_type": "polygon",
      "flags": {}
    },
    {
      "label": "cirtus11",
      "points": [
        [
          630.0,
          684.75
        ],
        [
          615.0,
          678.5
        ],
        [
          592.5,
          679.75
        ],
        [
          578.75,
          689.75
        ],
        [
          575.0,
          703.5
        ],
        [
          580.0,
          714.75
        ],
        [
          591,
          720
        ],
        [
          612,
          720
        ],
        [
          632,
          720
        ],
        [
          641.25,
          714.75
        ],
        [
          645.0,
          702.25
        ]
      ],
      "group_id": null,
      "shape_type": "polygon",
      "flags": {}
    },
    {
      "label": "cirtus12",
      "points": [
        [
          387.5,
          499.75
        ],
        [
          397.5,
          494.75
        ],
        [
          403.75,
          487.25
        ],
        [
          406.25,
          473.5
        ],
        [
          403.75,
          454.75
        ],
        [
          392.5,
          447.25
        ],
        [
          380.0,
          446.0
        ],
        [
          366.25,
          444.75
        ],
        [
          355.0,
          446.0
        ],
        [
          347.5,
          451.0
        ],
        [
          338.75,
          463.5
        ],
        [
          330.0,
          478.5
        ],
        [
          347.5,
          482.25
        ],
        [
          368.75,
          491.0
        ]
      ],
      "group_id": null,
      "shape_type": "polygon",
      "flags": {}
    },
    {
      "label": "cirtus13",
      "points": [
        [
          233.75,
          551.0
        ],
        [
          217.5,
          562.25
        ],
        [
          198.75,
          563.5
        ],
        [
          182.5,
          556.0
        ],
        [
          171.25,
          548.5
        ],
        [
          168.75,
          529.75
        ],
        [
          177.5,
          513.5
        ],
        [
          193.75,
          508.5
        ],
        [
          207.5,
          508.5
        ],
        [
          221.25,
          512.25
        ],
        [
          238.75,
          523.5
        ]
      ],
      "group_id": null,
      "shape_type": "polygon",
      "flags": {}
    }
  ],
  "imagePath": "hf303.jpg",
  "imageData": null,
  "imageHeight": 720,
  "imageWidth": 1280
}